rustmodels-0.1.26.dist-info/METADATA
rustmodels-0.1.26.dist-info/WHEEL
rustmodels/__init__.py
rustmodels/_rustmodels.cpython-38-x86_64-linux-gnu.so
rustmodels/_rustmodels.pyi
rustmodels/linreg.py
rustmodels/logreg.py
rustmodels/model_matrix.py
rustmodels/penalized_logreg.py
rustmodels-0.1.26.dist-info/RECORD
