Metadata-Version: 2.4
Name: rustmodels
Version: 0.1.26
Classifier: Programming Language :: Rust
Classifier: Programming Language :: Python :: Implementation :: CPython
Classifier: Programming Language :: Python :: Implementation :: PyPy
Requires-Dist: polars~=1.31
Requires-Dist: numpy~=2.3.1
Summary: A python package for statistical modeling with Rust's speed and R's syntax.
Keywords: rust,python,machine-learning,statistical-modeling
Author-email: Samuel Brown <brownasamuel1@gmail.com>
Maintainer-email: Samuel Brown <brownasamuel1@gmail.com>
License: MIT
Requires-Python: >=3.8
